partifact/__init__.py
partifact/auth_token.py
partifact/config.py
partifact/main.py
partifact/shell_commands.py
partifact-0.4.0.dist-info/METADATA
partifact-0.4.0.dist-info/WHEEL
partifact-0.4.0.dist-info/entry_points.txt
partifact-0.4.0.dist-info/licenses/LICENSE
partifact-0.4.0.dist-info/RECORD
