Metadata-Version: 2.4
Name: partifact
Version: 0.4.0
Summary: CodeArtifact utilties for Poetry
License: MIT
License-File: LICENSE
Author: David Steiner
Author-email: david_j_steiner@yahoo.co.nz
Requires-Python: >=3.10,<4.0
Classifier: License :: OSI Approved :: MIT License
Classifier: Programming Language :: Python :: 3
Classifier: Programming Language :: Python :: 3.10
Classifier: Programming Language :: Python :: 3.11
Classifier: Programming Language :: Python :: 3.12
Classifier: Programming Language :: Python :: 3.13
Classifier: Programming Language :: Python :: 3.14
Requires-Dist: boto3 (>=1.15,<2.0)
Requires-Dist: tomlkit (>=0.7.0,<1.0.0)
Requires-Dist: typer (>=0.19.0,<0.20.0)
Project-URL: Homepage, https://github.com/Validus-Risk-Management/partifact
